MANIFEST.in
README.md
setup.cfg
setup.py
better/__init__.py
better/lib.py
better_project_forecast.egg-info/PKG-INFO
better_project_forecast.egg-info/SOURCES.txt
better_project_forecast.egg-info/dependency_links.txt
better_project_forecast.egg-info/requires.txt
better_project_forecast.egg-info/top_level.txt
tests/test_better.py